osc2parser/__init__.py
osc2parser/openscenario2DenterHelper.py
osc2parser/openscenario2Lexer.py
osc2parser/openscenario2Listener.py
osc2parser/openscenario2Parser.py
osc2parser/openscenario2Visitor.py
osc2parser/osc2parser.py
py_osc2-0.1.0.dist-info/LICENSE
py_osc2-0.1.0.dist-info/METADATA
py_osc2-0.1.0.dist-info/WHEEL
py_osc2-0.1.0.dist-info/entry_points.txt
py_osc2-0.1.0.dist-info/top_level.txt
py_osc2-0.1.0.dist-info/RECORD
