Metadata-Version: 2.1
Name: py-osc2
Version: 0.1.0
Summary: PMSF Python support for OpenSCENARIO 2.x
Home-page: https://pmsf.eu/resources/osc2/py-osc2.html
Author: PMSF IT Consulting
Author-email: simulation@pmsf.eu
License: Mozilla Public License 2.0 (MPL 2.0)
Project-URL: Bug Tracker, https://github.com/PMSFIT/py-osc2/issues
Project-URL: Source Code, https://github.com/PMSFIT/py-osc2
Classifier: Development Status :: 3 - Alpha
Classifier: Environment :: Console
Classifier: License :: OSI Approved :: Mozilla Public License 2.0 (MPL 2.0)
Classifier: Operating System :: OS Independent
Classifier: Programming Language :: Python :: 3
Classifier: Programming Language :: Python :: 3 :: Only
Requires-Python: >=3.6, <4
License-File: LICENSE
Requires-Dist: antlr4-python3-runtime ==4.7.1
